dataQuest/__init__.py
dataQuest/filter_articles.py
dataQuest/generate_output.py
dataQuest/settings.py
dataQuest/utils.py
dataQuest/article_final_selection/__init__.py
dataQuest/article_final_selection/article_selector.py
dataQuest/article_final_selection/process_article.py
dataQuest/article_final_selection/process_articles.py
dataQuest/filter/__init__.py
dataQuest/filter/delpher_kranten.py
dataQuest/filter/document.py
dataQuest/filter/document_filter.py
dataQuest/filter/input_file.py
dataQuest/models/base.py
dataQuest/models/tfidf.py
dataQuest/output_generator/text_formater.py
dataQuest/preprocessor/__init__.py
dataQuest/preprocessor/parser.py
dataQuest/preprocessor/text_cleaner.py
dataQuest/temporal_categorization/__init__.py
dataQuest/temporal_categorization/timestamped_data.py
dataquest-0.1.1.dist-info/licenses/LICENSE
dataquest-0.1.1.dist-info/METADATA
dataquest-0.1.1.dist-info/WHEEL
dataquest-0.1.1.dist-info/entry_points.txt
dataquest-0.1.1.dist-info/top_level.txt
dataquest-0.1.1.dist-info/RECORD
