Metadata-Version: 2.4
Name: dataQuest
Version: 0.1.1
Summary: A package to extract hystorical news sentiments
Author-email: Parisa Zahedi <p.zahedi@uu.nl>, Shiva Nadi <s.nadi@uu.nl>
License: MIT
Classifier: Programming Language :: Python :: 3
Classifier: Programming Language :: Python :: 3.9
Classifier: Programming Language :: Python :: 3.10
Classifier: Programming Language :: Python :: 3.11
Classifier: Development Status :: 3 - Alpha
Classifier: License :: OSI Approved :: MIT License
Requires-Python: >=3.8
License-File: LICENSE
Requires-Dist: tqdm
Requires-Dist: pandas
Requires-Dist: pandas-stubs
Requires-Dist: types-tqdm
Requires-Dist: spacy==3.5.4
Requires-Dist: scikit-learn
Requires-Dist: numpy==1.26.4
Requires-Dist: scipy
Requires-Dist: flake8-pyproject
Requires-Dist: thinc==8.1.12
Provides-Extra: lint
Requires-Dist: flake8; extra == "lint"
Provides-Extra: test
Requires-Dist: pytest; extra == "test"
Requires-Dist: mypy; extra == "test"
Dynamic: license-file
